nitrolib/__init__.py
nitrolib/__main__.py
nitrolib/device.py
nitrolib/util.py
nitrolib/emulator/__init__.py
nitrolib/emulator/device.py
nitrolib/emulator/enums.py
nitrolib/resources/debugger_code.bin
nitrolib/resources/isid.bin
nitrolib-0.0.2.dist-info/LICENSE
nitrolib-0.0.2.dist-info/METADATA
nitrolib-0.0.2.dist-info/WHEEL
nitrolib-0.0.2.dist-info/entry_points.txt
nitrolib-0.0.2.dist-info/top_level.txt
nitrolib-0.0.2.dist-info/RECORD
